resp_benchmark-0.1.7.dist-info/METADATA
resp_benchmark-0.1.7.dist-info/WHEEL
resp_benchmark-0.1.7.dist-info/entry_points.txt
resp_benchmark-0.1.7.dist-info/license_files/LICENSE
resp_benchmark/cli.py
resp_benchmark/cores.py
resp_benchmark/__init__.py
resp_benchmark/wrapper.py
resp_benchmark/_resp_benchmark_rust_lib.pypy310-pp73-aarch64-linux-gnu.so
resp_benchmark-0.1.7.dist-info/RECORD
