Metadata-Version: 2.3
Name: resp-benchmark
Version: 0.1.7
Classifier: Programming Language :: Rust
Classifier: Programming Language :: Python :: Implementation :: CPython
Classifier: Programming Language :: Python :: Implementation :: PyPy
Requires-Dist: pydantic
Requires-Dist: redis
License-File: LICENSE
Summary: resp-benchmark is a benchmark tool for testing databases that support the RESP protocol, such as Redis, Valkey, and Tair.
Requires-Python: >=3.8
